flash_card/__init__.py
my_component/__init__.py
starter_component/__init__.py
streamlit_flashcard-0.0.1.dist-info/LICENSE
streamlit_flashcard-0.0.1.dist-info/METADATA
streamlit_flashcard-0.0.1.dist-info/WHEEL
streamlit_flashcard-0.0.1.dist-info/top_level.txt
streamlit_flashcard-0.0.1.dist-info/RECORD
